pysigrok_chrome_trace.py
pysigrok_format_chrome_trace-0.0.1.dist-info/entry_points.txt
pysigrok_format_chrome_trace-0.0.1.dist-info/LICENSE
pysigrok_format_chrome_trace-0.0.1.dist-info/WHEEL
pysigrok_format_chrome_trace-0.0.1.dist-info/METADATA
pysigrok_format_chrome_trace-0.0.1.dist-info/RECORD
