Metadata-Version: 2.1
Name: pysigrok-format-chrome-trace
Version: 0.0.1
Summary: PySigrok driver for chrome trace
Author-email: Scott Shawcroft <scott@tannewt.org>
Classifier: License :: OSI Approved :: MIT License
Project-URL: Home, https://github.com/pysigrok/format-chrome-trace
